{
	"format_version": "1.8.0",
	"animations": {
		"animation.model.work": {
			"loop": true,
			"animation_length": 0.48,
			"bones": {
				"bone4": {
					"rotation": {
						"0.0": {
							"vector": [0, 0, 0]
						},
						"0.48": {
							"vector": [0, 0, 90]
						}
					}
				},
				"bone2": {
					"rotation": {
						"0.0": {
							"vector": [0, 0, 0]
						},
						"0.48": {
							"vector": [0, 0, 90]
						}
					}
				},
				"rotate": {
					"scale": {
						"vector": [1, 1, 1]
					}
				},
				"bone": {
					"relative_to": {
						"rotation": "entity"
					},
					"rotation": [0, 0, 0.01],
					"position": {
						"0.0": {
							"vector": [0, 0, 0]
						},
						"0.48": {
							"vector": [2, 0, 0]
						}
					}
				},
				"bone3": {
					"position": {
						"0.0": {
							"vector": [0, 0, 0]
						},
						"0.48": {
							"vector": [0, -2, 0]
						}
					}
				},
				"bone5": {
					"position": {
						"0.0": {
							"vector": [0, 0, 0]
						},
						"0.48": {
							"vector": [-2, 0, 0]
						}
					}
				},
				"bone6": {
					"position": {
						"0.0": {
							"vector": [0, 0, 0]
						},
						"0.48": {
							"vector": [0, 2, 0]
						}
					}
				},
				"bone7": {
					"rotation": {
						"0.0": {
							"vector": [0, 0, 0]
						},
						"0.48": {
							"vector": [0, 0, 90]
						}
					}
				},
				"bone8": {
					"rotation": {
						"0.0": {
							"vector": [0, 0, 0]
						},
						"0.48": {
							"vector": [0, 0, 90]
						}
					}
				},
				"bone9": {
					"rotation": {
						"0.0": {
							"vector": [0, 0, 0]
						},
						"0.48": {
							"vector": [0, 0, 90]
						}
					}
				},
				"bone10": {
					"rotation": {
						"0.0": {
							"vector": [0, 0, 0]
						},
						"0.48": {
							"vector": [0, 0, 90]
						}
					}
				}
			}
		}
	},
	"geckolib_format_version": 2
}